{
  "user12": {
    "1": {
      "User": "user12",
      "n": 1,
      "EER": 0.16889312977109616,
      "AUC": 0.9167572215595112
    },
    "2": {
      "User": "user12",
      "n": 2,
      "EER": 0.12204724409448395,
      "AUC": 0.9469688232977187
    },
    "3": {
      "User": "user12",
      "n": 3,
      "EER": 0.09009009009009007,
      "AUC": 0.9622730932172696
    },
    "4": {
      "User": "user12",
      "n": 4,
      "EER": 0.08050847457706725,
      "AUC": 0.9729372279657109
    },
    "5": {
      "User": "user12",
      "n": 5,
      "EER": 0.07407407407392536,
      "AUC": 0.9789849765883318
    },
    "6": {
      "User": "user12",
      "n": 6,
      "EER": 0.06535947712417992,
      "AUC": 0.9848436930979626
    },
    "7": {
      "User": "user12",
      "n": 7,
      "EER": 0.04561403508626676,
      "AUC": 0.9881230854915066
    },
    "8": {
      "User": "user12",
      "n": 8,
      "EER": 0.0472279260785613,
      "AUC": 0.9881252179303399
    },
    "9": {
      "User": "user12",
      "n": 9,
      "EER": 0.04395604395604391,
      "AUC": 0.9885963093510263
    },
    "10": {
      "User": "user12",
      "n": 10,
      "EER": 0.04966442953175454,
      "AUC": 0.9897200851203143
    },
    "11": {
      "User": "user12",
      "n": 11,
      "EER": 0.03776435045231272,
      "AUC": 0.99330731789191
    },
    "12": {
      "User": "user12",
      "n": 12,
      "EER": 0.030303030304365,
      "AUC": 0.9938357938357938
    },
    "13": {
      "User": "user12",
      "n": 13,
      "EER": 0.02255639097828362,
      "AUC": 0.9944360902255639
    },
    "14": {
      "User": "user12",
      "n": 14,
      "EER": 0.02222222222223066,
      "AUC": 0.9957694095769409
    },
    "15": {
      "User": "user12",
      "n": 15,
      "EER": 0.0272727272739852,
      "AUC": 0.9960088691796009
    },
    "16": {
      "User": "user12",
      "n": 16,
      "EER": 0.02777777777779016,
      "AUC": 0.9966749792186201
    },
    "17": {
      "User": "user12",
      "n": 17,
      "EER": 0.021563342317519562,
      "AUC": 0.9967328269215061
    },
    "18": {
      "User": "user12",
      "n": 18,
      "EER": 0.01479289940845227,
      "AUC": 0.9977094865432334
    },
    "19": {
      "User": "user12",
      "n": 19,
      "EER": 0.016181229773501903,
      "AUC": 0.9968753487334002
    },
    "20": {
      "User": "user12",
      "n": 20,
      "EER": 0.010416666667619498,
      "AUC": 0.9987139917695473
    },
    "21": {
      "User": "user12",
      "n": 21,
      "EER": 0.01119402985186705,
      "AUC": 0.9989954075774972
    },
    "22": {
      "User": "user12",
      "n": 22,
      "EER": 0.0,
      "AUC": 1.0
    },
    "23": {
      "User": "user12",
      "n": 23,
      "EER": 0.008620689655948723,
      "AUC": 0.9996081504702194
    },
    "24": {
      "User": "user12",
      "n": 24,
      "EER": 0.00460829493173443,
      "AUC": 0.9997695852534563
    },
    "25": {
      "User": "user12",
      "n": 25,
      "EER": 0.0,
      "AUC": 1.0
    },
    "26": {
      "User": "user12",
      "n": 26,
      "EER": 0.0,
      "AUC": 1.0
    },
    "27": {
      "User": "user12",
      "n": 27,
      "EER": 0.0,
      "AUC": 1.0
    },
    "28": {
      "User": "user12",
      "n": 28,
      "EER": 0.0,
      "AUC": 1.0
    },
    "29": {
      "User": "user12",
      "n": 29,
      "EER": 0.0,
      "AUC": 1.0
    },
    "30": {
      "User": "user12",
      "n": 30,
      "EER": 0.0,
      "AUC": 1.0
    }
  },
  "user15": {
    "1": {
      "User": "user15",
      "n": 1,
      "EER": 0.15410385259631507,
      "AUC": 0.9283571585397358
    },
    "2": {
      "User": "user15",
      "n": 2,
      "EER": 0.10726643598615916,
      "AUC": 0.956441655341923
    },
    "3": {
      "User": "user15",
      "n": 3,
      "EER": 0.08152173913043485,
      "AUC": 0.973989283627606
    },
    "4": {
      "User": "user15",
      "n": 4,
      "EER": 0.08105687415960802,
      "AUC": 0.9758342493452212
    },
    "5": {
      "User": "user15",
      "n": 5,
      "EER": 0.05769230769229932,
      "AUC": 0.9846449872818174
    },
    "6": {
      "User": "user15",
      "n": 6,
      "EER": 0.04878048780487814,
      "AUC": 0.9901249256395003
    },
    "7": {
      "User": "user15",
      "n": 7,
      "EER": 0.04738154613459221,
      "AUC": 0.9931256514797662
    },
    "8": {
      "User": "user15",
      "n": 8,
      "EER": 0.03571428571429367,
      "AUC": 0.9923618861607143
    },
    "9": {
      "User": "user15",
      "n": 9,
      "EER": 0.043478260869562406,
      "AUC": 0.9951312137884025
    },
    "10": {
      "User": "user15",
      "n": 10,
      "EER": 0.03307888040829986,
      "AUC": 0.9957177434369763
    },
    "11": {
      "User": "user15",
      "n": 11,
      "EER": 0.017142857142217995,
      "AUC": 0.9983613445378151
    },
    "12": {
      "User": "user15",
      "n": 12,
      "EER": 0.022222222223596797,
      "AUC": 0.99688013136289
    },
    "13": {
      "User": "user15",
      "n": 13,
      "EER": 0.034050179211304585,
      "AUC": 0.9967144563918757
    },
    "14": {
      "User": "user15",
      "n": 14,
      "EER": 0.03180914512803011,
      "AUC": 0.9976143141153082
    },
    "15": {
      "User": "user15",
      "n": 15,
      "EER": 0.023809523811070404,
      "AUC": 0.998632946001367
    },
    "16": {
      "User": "user15",
      "n": 16,
      "EER": 0.023866348449012677,
      "AUC": 0.9985415009281358
    },
    "17": {
      "User": "user15",
      "n": 17,
      "EER": 0.03608247422628237,
      "AUC": 0.9974226804123711
    },
    "18": {
      "User": "user15",
      "n": 18,
      "EER": 0.028248587570874034,
      "AUC": 0.9979284369114878
    },
    "19": {
      "User": "user15",
      "n": 19,
      "EER": 0.018348623853961188,
      "AUC": 0.9980539338337503
    },
    "20": {
      "User": "user15",
      "n": 20,
      "EER": 0.016393442623823827,
      "AUC": 0.9973770491803279
    },
    "21": {
      "User": "user15",
      "n": 21,
      "EER": 0.013986013987315494,
      "AUC": 0.9982517482517482
    },
    "22": {
      "User": "user15",
      "n": 22,
      "EER": 0.01893939393953173,
      "AUC": 0.9968434343434344
    },
    "23": {
      "User": "user15",
      "n": 23,
      "EER": 0.01204819277135516,
      "AUC": 0.9975903614457831
    },
    "24": {
      "User": "user15",
      "n": 24,
      "EER": 0.012931034483451847,
      "AUC": 0.9974137931034482
    },
    "25": {
      "User": "user15",
      "n": 25,
      "EER": 0.01388888888932684,
      "AUC": 0.9965277777777778
    },
    "26": {
      "User": "user15",
      "n": 26,
      "EER": 0.020304568528070766,
      "AUC": 0.9898477157360407
    },
    "27": {
      "User": "user15",
      "n": 27,
      "EER": 0.0,
      "AUC": 1.0
    },
    "28": {
      "User": "user15",
      "n": 28,
      "EER": 0.0,
      "AUC": 1.0
    },
    "29": {
      "User": "user15",
      "n": 29,
      "EER": 0.0,
      "AUC": 1.0
    },
    "30": {
      "User": "user15",
      "n": 30,
      "EER": 0.0,
      "AUC": 1.0
    }
  },
  "user16": {
    "1": {
      "User": "user16",
      "n": 1,
      "EER": 0.1737541528254985,
      "AUC": 0.9108209251753758
    },
    "2": {
      "User": "user16",
      "n": 2,
      "EER": 0.14837398374029967,
      "AUC": 0.9378232762379105
    },
    "3": {
      "User": "user16",
      "n": 3,
      "EER": 0.12344827586208264,
      "AUC": 0.9532249099330933
    },
    "4": {
      "User": "user16",
      "n": 4,
      "EER": 0.09637987776113657,
      "AUC": 0.9643341116418359
    },
    "5": {
      "User": "user16",
      "n": 5,
      "EER": 0.08992805755473117,
      "AUC": 0.9721317682695949
    },
    "6": {
      "User": "user16",
      "n": 6,
      "EER": 0.0927152317880801,
      "AUC": 0.9768163439442274
    },
    "7": {
      "User": "user16",
      "n": 7,
      "EER": 0.08581436076993679,
      "AUC": 0.9787017682616802
    },
    "8": {
      "User": "user16",
      "n": 8,
      "EER": 0.07766990291267206,
      "AUC": 0.979618606592402
    },
    "9": {
      "User": "user16",
      "n": 9,
      "EER": 0.06896551724165174,
      "AUC": 0.9864821110571474
    },
    "10": {
      "User": "user16",
      "n": 10,
      "EER": 0.06391478029223094,
      "AUC": 0.9879809376971057
    },
    "11": {
      "User": "user16",
      "n": 11,
      "EER": 0.07335329341263966,
      "AUC": 0.987252767192887
    },
    "12": {
      "User": "user16",
      "n": 12,
      "EER": 0.04311774461140956,
      "AUC": 0.9923892442549159
    },
    "13": {
      "User": "user16",
      "n": 13,
      "EER": 0.04887218045202546,
      "AUC": 0.9936090225563909
    },
    "14": {
      "User": "user16",
      "n": 14,
      "EER": 0.056722689074490684,
      "AUC": 0.9929376005721438
    },
    "15": {
      "User": "user16",
      "n": 15,
      "EER": 0.0458715596335875,
      "AUC": 0.9931192660550459
    },
    "16": {
      "User": "user16",
      "n": 16,
      "EER": 0.05527638191044082,
      "AUC": 0.9911093931194435
    },
    "17": {
      "User": "user16",
      "n": 17,
      "EER": 0.04891304347785688,
      "AUC": 0.9924516908212561
    },
    "18": {
      "User": "user16",
      "n": 18,
      "EER": 0.03244837758000705,
      "AUC": 0.9970501474926253
    },
    "19": {
      "User": "user16",
      "n": 19,
      "EER": 0.03194888178795123,
      "AUC": 0.9968051118210863
    },
    "20": {
      "User": "user16",
      "n": 20,
      "EER": 0.01706484641685002,
      "AUC": 0.99813838039094
    },
    "21": {
      "User": "user16",
      "n": 21,
      "EER": 0.010989010989772448,
      "AUC": 0.9980812837955696
    },
    "22": {
      "User": "user16",
      "n": 22,
      "EER": 0.00796812749025239,
      "AUC": 0.9987418746068358
    },
    "23": {
      "User": "user16",
      "n": 23,
      "EER": 0.004219409283244529,
      "AUC": 0.9990071978158352
    },
    "24": {
      "User": "user16",
      "n": 24,
      "EER": 0.00450450450503951,
      "AUC": 0.9987987987987988
    },
    "25": {
      "User": "user16",
      "n": 25,
      "EER": 0.004878048780742874,
      "AUC": 0.9990243902439024
    },
    "26": {
      "User": "user16",
      "n": 26,
      "EER": 0.005347593584179026,
      "AUC": 0.9986631016042781
    },
    "27": {
      "User": "user16",
      "n": 27,
      "EER": 0.005917159764740453,
      "AUC": 0.9983862291554599
    },
    "28": {
      "User": "user16",
      "n": 28,
      "EER": 0.006493506493779371,
      "AUC": 0.9987012987012988
    },
    "29": {
      "User": "user16",
      "n": 29,
      "EER": 0.006711409396369747,
      "AUC": 0.9986577181208054
    },
    "30": {
      "User": "user16",
      "n": 30,
      "EER": 0.007194244604934532,
      "AUC": 0.9984012789768186
    }
  },
  "user20": {
    "1": {
      "User": "user20",
      "n": 1,
      "EER": 0.1565008025682171,
      "AUC": 0.9242659042525333
    },
    "2": {
      "User": "user20",
      "n": 2,
      "EER": 0.13798701298701338,
      "AUC": 0.9468207312318166
    },
    "3": {
      "User": "user20",
      "n": 3,
      "EER": 0.13684582743876217,
      "AUC": 0.9548816850797051
    },
    "4": {
      "User": "user20",
      "n": 4,
      "EER": 0.12913907284768208,
      "AUC": 0.9597079415626314
    },
    "5": {
      "User": "user20",
      "n": 5,
      "EER": 0.1278567016663455,
      "AUC": 0.9620846589014862
    },
    "6": {
      "User": "user20",
      "n": 6,
      "EER": 0.1249053747162065,
      "AUC": 0.9629377867725439
    },
    "7": {
      "User": "user20",
      "n": 7,
      "EER": 0.12650602409638553,
      "AUC": 0.9648466593647316
    },
    "8": {
      "User": "user20",
      "n": 8,
      "EER": 0.1299254526097417,
      "AUC": 0.9637232909614122
    },
    "9": {
      "User": "user20",
      "n": 9,
      "EER": 0.1200000000000305,
      "AUC": 0.9676953316953318
    },
    "10": {
      "User": "user20",
      "n": 10,
      "EER": 0.11888111888245081,
      "AUC": 0.9690934065934067
    },
    "11": {
      "User": "user20",
      "n": 11,
      "EER": 0.12244897959183988,
      "AUC": 0.968072134514183
    },
    "12": {
      "User": "user20",
      "n": 12,
      "EER": 0.10869565217391418,
      "AUC": 0.9697109117398973
    },
    "13": {
      "User": "user20",
      "n": 13,
      "EER": 0.12326043737564446,
      "AUC": 0.9694491280167099
    },
    "14": {
      "User": "user20",
      "n": 14,
      "EER": 0.10810810810816905,
      "AUC": 0.9684584361644495
    },
    "15": {
      "User": "user20",
      "n": 15,
      "EER": 0.10000000000003151,
      "AUC": 0.9716718804310045
    },
    "16": {
      "User": "user20",
      "n": 16,
      "EER": 0.09677419354839693,
      "AUC": 0.970494623655914
    },
    "17": {
      "User": "user20",
      "n": 17,
      "EER": 0.08196721311431561,
      "AUC": 0.9766285905462888
    },
    "18": {
      "User": "user20",
      "n": 18,
      "EER": 0.09090909090909094,
      "AUC": 0.9719166184134338
    },
    "19": {
      "User": "user20",
      "n": 19,
      "EER": 0.08391608391682535,
      "AUC": 0.9747848305540613
    },
    "20": {
      "User": "user20",
      "n": 20,
      "EER": 0.07843137254905572,
      "AUC": 0.9743018419489009
    },
    "21": {
      "User": "user20",
      "n": 21,
      "EER": 0.08695652173913052,
      "AUC": 0.9779978962131837
    },
    "22": {
      "User": "user20",
      "n": 22,
      "EER": 0.099999999999995,
      "AUC": 0.9743478260869565
    },
    "23": {
      "User": "user20",
      "n": 23,
      "EER": 0.07894736842104495,
      "AUC": 0.9814814814814815
    },
    "24": {
      "User": "user20",
      "n": 24,
      "EER": 0.060000000001237286,
      "AUC": 0.9816216216216216
    },
    "25": {
      "User": "user20",
      "n": 25,
      "EER": 0.0489130434770432,
      "AUC": 0.9898852657004831
    },
    "26": {
      "User": "user20",
      "n": 26,
      "EER": 0.023952095808070475,
      "AUC": 0.998877245508982
    },
    "27": {
      "User": "user20",
      "n": 27,
      "EER": 0.006622516556427456,
      "AUC": 0.9997716373601279
    },
    "28": {
      "User": "user20",
      "n": 28,
      "EER": 0.0,
      "AUC": 1.0
    },
    "29": {
      "User": "user20",
      "n": 29,
      "EER": 0.0,
      "AUC": 1.0
    },
    "30": {
      "User": "user20",
      "n": 30,
      "EER": 0.0,
      "AUC": 1.0
    }
  },
  "user21": {
    "1": {
      "User": "user21",
      "n": 1,
      "EER": 0.1204379562041546,
      "AUC": 0.9499419419648825
    },
    "2": {
      "User": "user21",
      "n": 2,
      "EER": 0.08929715872605404,
      "AUC": 0.9725756067281223
    },
    "3": {
      "User": "user21",
      "n": 3,
      "EER": 0.05619078732347409,
      "AUC": 0.9851487193352033
    },
    "4": {
      "User": "user21",
      "n": 4,
      "EER": 0.054861730596695114,
      "AUC": 0.9907276459026857
    },
    "5": {
      "User": "user21",
      "n": 5,
      "EER": 0.042105263157894715,
      "AUC": 0.9924888796011584
    },
    "6": {
      "User": "user21",
      "n": 6,
      "EER": 0.04244954766772793,
      "AUC": 0.9949286708420321
    },
    "7": {
      "User": "user21",
      "n": 7,
      "EER": 0.034024896266576336,
      "AUC": 0.9957145772396435
    },
    "8": {
      "User": "user21",
      "n": 8,
      "EER": 0.034046692606083576,
      "AUC": 0.9960341215205027
    },
    "9": {
      "User": "user21",
      "n": 9,
      "EER": 0.04026845637457522,
      "AUC": 0.9968680089485459
    },
    "10": {
      "User": "user21",
      "n": 10,
      "EER": 0.025641025641025838,
      "AUC": 0.9978849407783418
    },
    "11": {
      "User": "user21",
      "n": 11,
      "EER": 0.007142857143731029,
      "AUC": 0.9991596638655462
    },
    "12": {
      "User": "user21",
      "n": 12,
      "EER": 0.003184713375868232,
      "AUC": 0.9993322375179782
    },
    "13": {
      "User": "user21",
      "n": 13,
      "EER": 0.0035906642740245213,
      "AUC": 0.9997127468581688
    },
    "14": {
      "User": "user21",
      "n": 14,
      "EER": 0.0019841269841953265,
      "AUC": 0.9998955722639933
    },
    "15": {
      "User": "user21",
      "n": 15,
      "EER": 0.0043290043299164735,
      "AUC": 0.9997721576668945
    },
    "16": {
      "User": "user21",
      "n": 16,
      "EER": 0.0070921985825549445,
      "AUC": 0.9994934143870314
    },
    "17": {
      "User": "user21",
      "n": 17,
      "EER": 0.015345268543200574,
      "AUC": 0.9988195947275231
    },
    "18": {
      "User": "user21",
      "n": 18,
      "EER": 0.005602240897419201,
      "AUC": 0.9995331465919701
    },
    "19": {
      "User": "user21",
      "n": 19,
      "EER": 0.003058103975649607,
      "AUC": 0.9997219905476786
    },
    "20": {
      "User": "user21",
      "n": 20,
      "EER": 0.0,
      "AUC": 1.0
    },
    "21": {
      "User": "user21",
      "n": 21,
      "EER": 0.0,
      "AUC": 1.0
    },
    "22": {
      "User": "user21",
      "n": 22,
      "EER": 0.0,
      "AUC": 1.0
    },
    "23": {
      "User": "user21",
      "n": 23,
      "EER": 0.0,
      "AUC": 1.0
    },
    "24": {
      "User": "user21",
      "n": 24,
      "EER": 0.0,
      "AUC": 1.0
    },
    "25": {
      "User": "user21",
      "n": 25,
      "EER": 0.0,
      "AUC": 1.0
    },
    "26": {
      "User": "user21",
      "n": 26,
      "EER": 0.0,
      "AUC": 1.0
    },
    "27": {
      "User": "user21",
      "n": 27,
      "EER": 0.0,
      "AUC": 1.0
    },
    "28": {
      "User": "user21",
      "n": 28,
      "EER": 0.0,
      "AUC": 1.0
    },
    "29": {
      "User": "user21",
      "n": 29,
      "EER": 0.0,
      "AUC": 1.0
    },
    "30": {
      "User": "user21",
      "n": 30,
      "EER": 0.0,
      "AUC": 1.0
    }
  },
  "user23": {
    "1": {
      "User": "user23",
      "n": 1,
      "EER": 0.16351280710903845,
      "AUC": 0.9147363859486161
    },
    "2": {
      "User": "user23",
      "n": 2,
      "EER": 0.14396887159532068,
      "AUC": 0.9376875923699228
    },
    "3": {
      "User": "user23",
      "n": 3,
      "EER": 0.12096511248798486,
      "AUC": 0.9512844100796498
    },
    "4": {
      "User": "user23",
      "n": 4,
      "EER": 0.11353517364063567,
      "AUC": 0.9571301361149981
    },
    "5": {
      "User": "user23",
      "n": 5,
      "EER": 0.1000000000000965,
      "AUC": 0.964360231271996
    },
    "6": {
      "User": "user23",
      "n": 6,
      "EER": 0.12249134947996959,
      "AUC": 0.9644655901576316
    },
    "7": {
      "User": "user23",
      "n": 7,
      "EER": 0.09709543568431112,
      "AUC": 0.9707094755458812
    },
    "8": {
      "User": "user23",
      "n": 8,
      "EER": 0.09999999999999996,
      "AUC": 0.9704077669902913
    },
    "9": {
      "User": "user23",
      "n": 9,
      "EER": 0.07382550335667884,
      "AUC": 0.9767337807606264
    },
    "10": {
      "User": "user23",
      "n": 10,
      "EER": 0.09374999999999997,
      "AUC": 0.9720125786163523
    },
    "11": {
      "User": "user23",
      "n": 11,
      "EER": 0.09999999999999978,
      "AUC": 0.9726799242424242
    },
    "12": {
      "User": "user23",
      "n": 12,
      "EER": 0.07142857142857141,
      "AUC": 0.9782091917591126
    },
    "13": {
      "User": "user23",
      "n": 13,
      "EER": 0.08000000000000441,
      "AUC": 0.9821184919210053
    },
    "14": {
      "User": "user23",
      "n": 14,
      "EER": 0.09090909090909094,
      "AUC": 0.9826710215931773
    },
    "15": {
      "User": "user23",
      "n": 15,
      "EER": 0.05882352941182945,
      "AUC": 0.9866886409736308
    },
    "16": {
      "User": "user23",
      "n": 16,
      "EER": 0.07142857142857137,
      "AUC": 0.9858156028368794
    },
    "17": {
      "User": "user23",
      "n": 17,
      "EER": 0.07142857142857137,
      "AUC": 0.9873626373626373
    },
    "18": {
      "User": "user23",
      "n": 18,
      "EER": 0.08333333333333032,
      "AUC": 0.9873949579831933
    },
    "19": {
      "User": "user23",
      "n": 19,
      "EER": 0.07951070336385715,
      "AUC": 0.9880455935501806
    },
    "20": {
      "User": "user23",
      "n": 20,
      "EER": 0.019607843138157544,
      "AUC": 0.9967320261437909
    },
    "21": {
      "User": "user23",
      "n": 21,
      "EER": 0.017482517482652275,
      "AUC": 0.9956293706293706
    },
    "22": {
      "User": "user23",
      "n": 22,
      "EER": 0.01526717557277909,
      "AUC": 0.9961832061068702
    },
    "23": {
      "User": "user23",
      "n": 23,
      "EER": 0.012195121952282487,
      "AUC": 0.9964430894308943
    },
    "24": {
      "User": "user23",
      "n": 24,
      "EER": 0.013100436681280515,
      "AUC": 0.9967248908296943
    },
    "25": {
      "User": "user23",
      "n": 25,
      "EER": 0.009389671361812183,
      "AUC": 0.9986586183769283
    },
    "26": {
      "User": "user23",
      "n": 26,
      "EER": 0.005208333333749712,
      "AUC": 0.9992559523809523
    },
    "27": {
      "User": "user23",
      "n": 27,
      "EER": 0.0,
      "AUC": 1.0
    },
    "28": {
      "User": "user23",
      "n": 28,
      "EER": 0.0,
      "AUC": 1.0
    },
    "29": {
      "User": "user23",
      "n": 29,
      "EER": 0.0,
      "AUC": 1.0
    },
    "30": {
      "User": "user23",
      "n": 30,
      "EER": 0.0,
      "AUC": 1.0
    }
  },
  "user29": {
    "1": {
      "User": "user29",
      "n": 1,
      "EER": 0.1641791044772306,
      "AUC": 0.9306155188967443
    },
    "2": {
      "User": "user29",
      "n": 2,
      "EER": 0.14482758620699973,
      "AUC": 0.9438062862898448
    },
    "3": {
      "User": "user29",
      "n": 3,
      "EER": 0.12903225806476226,
      "AUC": 0.9497296839788824
    },
    "4": {
      "User": "user29",
      "n": 4,
      "EER": 0.1340206185560172,
      "AUC": 0.9554479953437653
    },
    "5": {
      "User": "user29",
      "n": 5,
      "EER": 0.11617312072825006,
      "AUC": 0.9568538121398902
    },
    "6": {
      "User": "user29",
      "n": 6,
      "EER": 0.12345679012345678,
      "AUC": 0.9617249561539255
    },
    "7": {
      "User": "user29",
      "n": 7,
      "EER": 0.11594202898551538,
      "AUC": 0.9616674536583003
    },
    "8": {
      "User": "user29",
      "n": 8,
      "EER": 0.11056751467756538,
      "AUC": 0.9605742627707673
    },
    "9": {
      "User": "user29",
      "n": 9,
      "EER": 0.10862262037994475,
      "AUC": 0.9647743317590924
    },
    "10": {
      "User": "user29",
      "n": 10,
      "EER": 0.09681528662553153,
      "AUC": 0.9645738550197149
    },
    "11": {
      "User": "user29",
      "n": 11,
      "EER": 0.10300429184655838,
      "AUC": 0.9625178826895565
    },
    "12": {
      "User": "user29",
      "n": 12,
      "EER": 0.09409888357287888,
      "AUC": 0.9668560606060606
    },
    "13": {
      "User": "user29",
      "n": 13,
      "EER": 0.10126582278331167,
      "AUC": 0.9660784435991769
    },
    "14": {
      "User": "user29",
      "n": 14,
      "EER": 0.11623246492888613,
      "AUC": 0.9625918503674014
    },
    "15": {
      "User": "user29",
      "n": 15,
      "EER": 0.12147505423066929,
      "AUC": 0.9597613882863341
    },
    "16": {
      "User": "user29",
      "n": 16,
      "EER": 0.11961722488071325,
      "AUC": 0.9570637119113574
    },
    "17": {
      "User": "user29",
      "n": 17,
      "EER": 0.12499999999999939,
      "AUC": 0.9589239690721649
    },
    "18": {
      "User": "user29",
      "n": 18,
      "EER": 0.09090909090909098,
      "AUC": 0.9713052310817675
    },
    "19": {
      "User": "user29",
      "n": 19,
      "EER": 0.09999999999999994,
      "AUC": 0.9722560975609756
    },
    "20": {
      "User": "user29",
      "n": 20,
      "EER": 0.11400651465785973,
      "AUC": 0.9690553745928339
    },
    "21": {
      "User": "user29",
      "n": 21,
      "EER": 0.11149825783967594,
      "AUC": 0.9651567944250872
    },
    "22": {
      "User": "user29",
      "n": 22,
      "EER": 0.1203007518808413,
      "AUC": 0.950187969924812
    },
    "23": {
      "User": "user29",
      "n": 23,
      "EER": 0.051792828685447545,
      "AUC": 0.9694555112881806
    },
    "24": {
      "User": "user29",
      "n": 24,
      "EER": 0.04700854700967119,
      "AUC": 0.9729344729344729
    },
    "25": {
      "User": "user29",
      "n": 25,
      "EER": 0.027522935779859353,
      "AUC": 0.9862385321100917
    },
    "26": {
      "User": "user29",
      "n": 26,
      "EER": 0.030456852792138677,
      "AUC": 0.984771573604061
    },
    "27": {
      "User": "user29",
      "n": 27,
      "EER": 0.0,
      "AUC": 1.0
    },
    "28": {
      "User": "user29",
      "n": 28,
      "EER": 0.0,
      "AUC": 1.0
    },
    "29": {
      "User": "user29",
      "n": 29,
      "EER": 0.0,
      "AUC": 1.0
    },
    "30": {
      "User": "user29",
      "n": 30,
      "EER": 0.0,
      "AUC": 1.0
    }
  },
  "user35": {
    "1": {
      "User": "user35",
      "n": 1,
      "EER": 0.2151647893195849,
      "AUC": 0.8795962590778927
    },
    "2": {
      "User": "user35",
      "n": 2,
      "EER": 0.17916489135181013,
      "AUC": 0.9010713609403427
    },
    "3": {
      "User": "user35",
      "n": 3,
      "EER": 0.17610062893081765,
      "AUC": 0.9104468762012251
    },
    "4": {
      "User": "user35",
      "n": 4,
      "EER": 0.17241379310319616,
      "AUC": 0.916365127796262
    },
    "5": {
      "User": "user35",
      "n": 5,
      "EER": 0.1789949181244619,
      "AUC": 0.9234603477482038
    },
    "6": {
      "User": "user35",
      "n": 6,
      "EER": 0.17219917012514172,
      "AUC": 0.92380145325619
    },
    "7": {
      "User": "user35",
      "n": 7,
      "EER": 0.13741721854454234,
      "AUC": 0.9339889244119661
    },
    "8": {
      "User": "user35",
      "n": 8,
      "EER": 0.1389698736645173,
      "AUC": 0.9322967282150956
    },
    "9": {
      "User": "user35",
      "n": 9,
      "EER": 0.1270903010037923,
      "AUC": 0.9391888304931784
    },
    "10": {
      "User": "user35",
      "n": 10,
      "EER": 0.13888888888888876,
      "AUC": 0.9406166596432084
    },
    "11": {
      "User": "user35",
      "n": 11,
      "EER": 0.16666666666666669,
      "AUC": 0.931344696969697
    },
    "12": {
      "User": "user35",
      "n": 12,
      "EER": 0.15384615384615438,
      "AUC": 0.9362012395187751
    },
    "13": {
      "User": "user35",
      "n": 13,
      "EER": 0.1341681574246496,
      "AUC": 0.9425993622151357
    },
    "14": {
      "User": "user35",
      "n": 14,
      "EER": 0.14285714285700266,
      "AUC": 0.9421362170366154
    },
    "15": {
      "User": "user35",
      "n": 15,
      "EER": 0.17710583153393933,
      "AUC": 0.9384449244060475
    },
    "16": {
      "User": "user35",
      "n": 16,
      "EER": 0.17619047619044065,
      "AUC": 0.9427170868347338
    },
    "17": {
      "User": "user35",
      "n": 17,
      "EER": 0.13333333333381264,
      "AUC": 0.9544130248500429
    },
    "18": {
      "User": "user35",
      "n": 18,
      "EER": 0.13202247190987887,
      "AUC": 0.9673725151253241
    },
    "19": {
      "User": "user35",
      "n": 19,
      "EER": 0.11963190184140846,
      "AUC": 0.9690695296523517
    },
    "20": {
      "User": "user35",
      "n": 20,
      "EER": 0.11764705882463372,
      "AUC": 0.9633260711692084
    },
    "21": {
      "User": "user35",
      "n": 21,
      "EER": 0.12499999999999814,
      "AUC": 0.9645979020979021
    },
    "22": {
      "User": "user35",
      "n": 22,
      "EER": 0.14068441064636858,
      "AUC": 0.9614340032590983
    },
    "23": {
      "User": "user35",
      "n": 23,
      "EER": 0.14056224899545772,
      "AUC": 0.9662650602409638
    },
    "24": {
      "User": "user35",
      "n": 24,
      "EER": 0.14224137930965708,
      "AUC": 0.9646551724137931
    },
    "25": {
      "User": "user35",
      "n": 25,
      "EER": 0.13425925925916005,
      "AUC": 0.9606481481481481
    },
    "26": {
      "User": "user35",
      "n": 26,
      "EER": 0.10256410256411162,
      "AUC": 0.9692307692307692
    },
    "27": {
      "User": "user35",
      "n": 27,
      "EER": 0.10169491525440016,
      "AUC": 0.96045197740113
    },
    "28": {
      "User": "user35",
      "n": 28,
      "EER": 0.0925925925942206,
      "AUC": 0.9506172839506173
    },
    "29": {
      "User": "user35",
      "n": 29,
      "EER": 0.08280254777085122,
      "AUC": 0.9585987261146497
    },
    "30": {
      "User": "user35",
      "n": 30,
      "EER": 0.05479452054824149,
      "AUC": 0.9726027397260274
    }
  },
  "user7": {
    "1": {
      "User": "user7",
      "n": 1,
      "EER": 0.06456382454411039,
      "AUC": 0.9798346626870496
    },
    "2": {
      "User": "user7",
      "n": 2,
      "EER": 0.05580923389193993,
      "AUC": 0.9858235753081029
    },
    "3": {
      "User": "user7",
      "n": 3,
      "EER": 0.050136027983971536,
      "AUC": 0.987965897309147
    },
    "4": {
      "User": "user7",
      "n": 4,
      "EER": 0.040567951318458424,
      "AUC": 0.9903542761047832
    },
    "5": {
      "User": "user7",
      "n": 5,
      "EER": 0.03474114441429355,
      "AUC": 0.9924386920980927
    },
    "6": {
      "User": "user7",
      "n": 6,
      "EER": 0.030150753768265676,
      "AUC": 0.992672340028315
    },
    "7": {
      "User": "user7",
      "n": 7,
      "EER": 0.036496350364963404,
      "AUC": 0.993145897103838
    },
    "8": {
      "User": "user7",
      "n": 8,
      "EER": 0.032066508313321196,
      "AUC": 0.9939769256871395
    },
    "9": {
      "User": "user7",
      "n": 9,
      "EER": 0.03017832647487655,
      "AUC": 0.9960088836632046
    },
    "10": {
      "User": "user7",
      "n": 10,
      "EER": 0.02184087363554869,
      "AUC": 0.9959740325096875
    },
    "11": {
      "User": "user7",
      "n": 11,
      "EER": 0.02659574467995775,
      "AUC": 0.9967667918231122
    },
    "12": {
      "User": "user7",
      "n": 12,
      "EER": 0.031496062991352464,
      "AUC": 0.9964019398237471
    },
    "13": {
      "User": "user7",
      "n": 13,
      "EER": 0.02262443438932465,
      "AUC": 0.9960892049127343
    },
    "14": {
      "User": "user7",
      "n": 14,
      "EER": 0.022670025189783484,
      "AUC": 0.9962416536723842
    },
    "15": {
      "User": "user7",
      "n": 15,
      "EER": 0.0219178082183248,
      "AUC": 0.9979924421350969
    },
    "16": {
      "User": "user7",
      "n": 16,
      "EER": 0.01818181818181809,
      "AUC": 0.9973033083124826
    },
    "17": {
      "User": "user7",
      "n": 17,
      "EER": 0.022950819673330645,
      "AUC": 0.9982447425070375
    },
    "18": {
      "User": "user7",
      "n": 18,
      "EER": 0.02083333333333332,
      "AUC": 0.9986263736263736
    },
    "19": {
      "User": "user7",
      "n": 19,
      "EER": 0.022471910112360875,
      "AUC": 0.9973827895853075
    },
    "20": {
      "User": "user7",
      "n": 20,
      "EER": 0.02325581395348018,
      "AUC": 0.9982735858637148
    },
    "21": {
      "User": "user7",
      "n": 21,
      "EER": 0.02469135802469131,
      "AUC": 0.9982032110357619
    },
    "22": {
      "User": "user7",
      "n": 22,
      "EER": 0.0156250000000369,
      "AUC": 0.9988648504273504
    },
    "23": {
      "User": "user7",
      "n": 23,
      "EER": 0.016759776538271605,
      "AUC": 0.9991806331471136
    },
    "24": {
      "User": "user7",
      "n": 24,
      "EER": 0.017751479290389092,
      "AUC": 0.9980856247824574
    },
    "25": {
      "User": "user7",
      "n": 25,
      "EER": 0.01562500000000485,
      "AUC": 0.9988982371794872
    },
    "26": {
      "User": "user7",
      "n": 26,
      "EER": 0.021739130435234857,
      "AUC": 0.9982181040627227
    },
    "27": {
      "User": "user7",
      "n": 27,
      "EER": 0.016393442623017694,
      "AUC": 0.999152063312606
    },
    "28": {
      "User": "user7",
      "n": 28,
      "EER": 0.00900900900968937,
      "AUC": 0.9994900560938297
    },
    "29": {
      "User": "user7",
      "n": 29,
      "EER": 0.01960784313725501,
      "AUC": 0.9989106753812637
    },
    "30": {
      "User": "user7",
      "n": 30,
      "EER": 0.020833333333333415,
      "AUC": 0.9991666666666666
    }
  },
  "user9": {
    "1": {
      "User": "user9",
      "n": 1,
      "EER": 0.003415883859636202,
      "AUC": 0.9997800426307017
    },
    "2": {
      "User": "user9",
      "n": 2,
      "EER": 0.000500125031427448,
      "AUC": 0.9999931345032668
    },
    "3": {
      "User": "user9",
      "n": 3,
      "EER": 0.0,
      "AUC": 1.0
    },
    "4": {
      "User": "user9",
      "n": 4,
      "EER": 0.0,
      "AUC": 1.0
    },
    "5": {
      "User": "user9",
      "n": 5,
      "EER": 0.0,
      "AUC": 1.0
    },
    "6": {
      "User": "user9",
      "n": 6,
      "EER": 0.0,
      "AUC": 1.0
    },
    "7": {
      "User": "user9",
      "n": 7,
      "EER": 0.0,
      "AUC": 1.0
    },
    "8": {
      "User": "user9",
      "n": 8,
      "EER": 0.0,
      "AUC": 1.0
    },
    "9": {
      "User": "user9",
      "n": 9,
      "EER": 0.0,
      "AUC": 1.0
    },
    "10": {
      "User": "user9",
      "n": 10,
      "EER": 0.0,
      "AUC": 1.0
    },
    "11": {
      "User": "user9",
      "n": 11,
      "EER": 0.0,
      "AUC": 1.0
    },
    "12": {
      "User": "user9",
      "n": 12,
      "EER": 0.0,
      "AUC": 1.0
    },
    "13": {
      "User": "user9",
      "n": 13,
      "EER": 0.0,
      "AUC": 1.0
    },
    "14": {
      "User": "user9",
      "n": 14,
      "EER": 0.0,
      "AUC": 1.0
    },
    "15": {
      "User": "user9",
      "n": 15,
      "EER": 0.0,
      "AUC": 1.0
    },
    "16": {
      "User": "user9",
      "n": 16,
      "EER": 0.0,
      "AUC": 1.0
    },
    "17": {
      "User": "user9",
      "n": 17,
      "EER": 0.0,
      "AUC": 1.0
    },
    "18": {
      "User": "user9",
      "n": 18,
      "EER": 0.0,
      "AUC": 1.0
    },
    "19": {
      "User": "user9",
      "n": 19,
      "EER": 0.0,
      "AUC": 1.0
    },
    "20": {
      "User": "user9",
      "n": 20,
      "EER": 0.0,
      "AUC": 1.0
    },
    "21": {
      "User": "user9",
      "n": 21,
      "EER": 0.0,
      "AUC": 1.0
    },
    "22": {
      "User": "user9",
      "n": 22,
      "EER": 0.0,
      "AUC": 1.0
    },
    "23": {
      "User": "user9",
      "n": 23,
      "EER": 0.0,
      "AUC": 1.0
    },
    "24": {
      "User": "user9",
      "n": 24,
      "EER": 0.0,
      "AUC": 1.0
    },
    "25": {
      "User": "user9",
      "n": 25,
      "EER": 0.0,
      "AUC": 1.0
    },
    "26": {
      "User": "user9",
      "n": 26,
      "EER": 0.0,
      "AUC": 1.0
    },
    "27": {
      "User": "user9",
      "n": 27,
      "EER": 0.0,
      "AUC": 1.0
    },
    "28": {
      "User": "user9",
      "n": 28,
      "EER": 0.0,
      "AUC": 1.0
    },
    "29": {
      "User": "user9",
      "n": 29,
      "EER": 0.0,
      "AUC": 1.0
    },
    "30": {
      "User": "user9",
      "n": 30,
      "EER": 0.0,
      "AUC": 1.0
    }
  }
}