{
  "0": {
    "1": {
      "User": 0,
      "n": 1,
      "EER": 0.1919647482586776,
      "AUC": 0.889773385470585
    },
    "2": {
      "User": 0,
      "n": 2,
      "EER": 0.1701492537313433,
      "AUC": 0.9092621045270053
    },
    "3": {
      "User": 0,
      "n": 3,
      "EER": 0.1592553152425885,
      "AUC": 0.9182450642485603
    },
    "4": {
      "User": 0,
      "n": 4,
      "EER": 0.1524609843937576,
      "AUC": 0.9233061441725993
    },
    "5": {
      "User": 0,
      "n": 5,
      "EER": 0.1566265060240977,
      "AUC": 0.9268537107982283
    },
    "6": {
      "User": 0,
      "n": 6,
      "EER": 0.15163161979239959,
      "AUC": 0.9296364487925122
    },
    "7": {
      "User": 0,
      "n": 7,
      "EER": 0.14830508474576903,
      "AUC": 0.9310363703613731
    },
    "8": {
      "User": 0,
      "n": 8,
      "EER": 0.14837147234753673,
      "AUC": 0.9329347087018756
    },
    "9": {
      "User": 0,
      "n": 9,
      "EER": 0.15068493150684917,
      "AUC": 0.9343283536545828
    },
    "10": {
      "User": 0,
      "n": 10,
      "EER": 0.1486436269031828,
      "AUC": 0.9356287674662891
    }
  },
  "1": {
    "1": {
      "User": 1,
      "n": 1,
      "EER": 0.15025368381225224,
      "AUC": 0.9369865267623422
    },
    "2": {
      "User": 1,
      "n": 2,
      "EER": 0.11163585106791547,
      "AUC": 0.9619812784675862
    },
    "3": {
      "User": 1,
      "n": 3,
      "EER": 0.09453839756029934,
      "AUC": 0.9730018035985383
    },
    "4": {
      "User": 1,
      "n": 4,
      "EER": 0.08308605341246293,
      "AUC": 0.9791734014229904
    },
    "5": {
      "User": 1,
      "n": 5,
      "EER": 0.07459612537905402,
      "AUC": 0.9830607825993539
    },
    "6": {
      "User": 1,
      "n": 6,
      "EER": 0.06714424007685244,
      "AUC": 0.9854611815684649
    },
    "7": {
      "User": 1,
      "n": 7,
      "EER": 0.06256220030672285,
      "AUC": 0.9877349419818592
    },
    "8": {
      "User": 1,
      "n": 8,
      "EER": 0.0577211394302832,
      "AUC": 0.989069858421729
    },
    "9": {
      "User": 1,
      "n": 9,
      "EER": 0.05325443786970978,
      "AUC": 0.9905239527019812
    },
    "10": {
      "User": 1,
      "n": 10,
      "EER": 0.05164806644126875,
      "AUC": 0.9911149200605768
    }
  },
  "2": {
    "1": {
      "User": 2,
      "n": 1,
      "EER": 0.17222483945325961,
      "AUC": 0.90725952166321
    },
    "2": {
      "User": 2,
      "n": 2,
      "EER": 0.14781096689973047,
      "AUC": 0.9274790522726901
    },
    "3": {
      "User": 2,
      "n": 3,
      "EER": 0.1352418558738381,
      "AUC": 0.9363928187018611
    },
    "4": {
      "User": 2,
      "n": 4,
      "EER": 0.12755929075528274,
      "AUC": 0.9422702871040186
    },
    "5": {
      "User": 2,
      "n": 5,
      "EER": 0.12788954142140163,
      "AUC": 0.946179284234143
    },
    "6": {
      "User": 2,
      "n": 6,
      "EER": 0.11962118080177137,
      "AUC": 0.949926168386088
    },
    "7": {
      "User": 2,
      "n": 7,
      "EER": 0.11525029103568367,
      "AUC": 0.9516089157807468
    },
    "8": {
      "User": 2,
      "n": 8,
      "EER": 0.11631016042780755,
      "AUC": 0.9546495333319536
    },
    "9": {
      "User": 2,
      "n": 9,
      "EER": 0.1098714390897175,
      "AUC": 0.9562454303624498
    },
    "10": {
      "User": 2,
      "n": 10,
      "EER": 0.10557480314973222,
      "AUC": 0.9584054986437731
    }
  },
  "3": {
    "1": {
      "User": 3,
      "n": 1,
      "EER": 0.1668674698795187,
      "AUC": 0.9190285866933019
    },
    "2": {
      "User": 3,
      "n": 2,
      "EER": 0.14170692431562887,
      "AUC": 0.9370023081118268
    },
    "3": {
      "User": 3,
      "n": 3,
      "EER": 0.13437042256136017,
      "AUC": 0.9445918498085212
    },
    "4": {
      "User": 3,
      "n": 4,
      "EER": 0.1308751423902341,
      "AUC": 0.9492583670356523
    },
    "5": {
      "User": 3,
      "n": 5,
      "EER": 0.12576064908722104,
      "AUC": 0.9529328173609739
    },
    "6": {
      "User": 3,
      "n": 6,
      "EER": 0.1201806441982589,
      "AUC": 0.955814903699111
    },
    "7": {
      "User": 3,
      "n": 7,
      "EER": 0.12285714285714285,
      "AUC": 0.9579911804275251
    },
    "8": {
      "User": 3,
      "n": 8,
      "EER": 0.12249176400019626,
      "AUC": 0.9592416296551182
    },
    "9": {
      "User": 3,
      "n": 9,
      "EER": 0.12104283054003781,
      "AUC": 0.9600721215386138
    },
    "10": {
      "User": 3,
      "n": 10,
      "EER": 0.11572626047831323,
      "AUC": 0.9616906194357435
    }
  },
  "4": {
    "1": {
      "User": 4,
      "n": 1,
      "EER": 0.050132281611117546,
      "AUC": 0.9856343338063909
    },
    "2": {
      "User": 4,
      "n": 2,
      "EER": 0.026884755078998547,
      "AUC": 0.990016600712707
    },
    "3": {
      "User": 4,
      "n": 3,
      "EER": 0.023651391039900153,
      "AUC": 0.9909510267608563
    },
    "4": {
      "User": 4,
      "n": 4,
      "EER": 0.01980929854471825,
      "AUC": 0.9911737669524796
    },
    "5": {
      "User": 4,
      "n": 5,
      "EER": 0.018515661163265182,
      "AUC": 0.9912502183361632
    },
    "6": {
      "User": 4,
      "n": 6,
      "EER": 0.01860447844220825,
      "AUC": 0.9914032653114196
    },
    "7": {
      "User": 4,
      "n": 7,
      "EER": 0.01769604441364418,
      "AUC": 0.9912323667711599
    },
    "8": {
      "User": 4,
      "n": 8,
      "EER": 0.01747852425640098,
      "AUC": 0.9912615229294742
    },
    "9": {
      "User": 4,
      "n": 9,
      "EER": 0.01706866640430974,
      "AUC": 0.9910844894354387
    },
    "10": {
      "User": 4,
      "n": 10,
      "EER": 0.01719901719901741,
      "AUC": 0.9911210849839008
    }
  },
  "5": {
    "1": {
      "User": 5,
      "n": 1,
      "EER": 0.19183337900794734,
      "AUC": 0.8915195832994763
    },
    "2": {
      "User": 5,
      "n": 2,
      "EER": 0.1649257833974711,
      "AUC": 0.911924241406799
    },
    "3": {
      "User": 5,
      "n": 3,
      "EER": 0.15337784399182913,
      "AUC": 0.9217375710423219
    },
    "4": {
      "User": 5,
      "n": 4,
      "EER": 0.1461521456118334,
      "AUC": 0.9276395088354227
    },
    "5": {
      "User": 5,
      "n": 5,
      "EER": 0.13918286980174593,
      "AUC": 0.9317181717572709
    },
    "6": {
      "User": 5,
      "n": 6,
      "EER": 0.13188647746243748,
      "AUC": 0.9355919671383494
    },
    "7": {
      "User": 5,
      "n": 7,
      "EER": 0.1308593750000201,
      "AUC": 0.9374871193754324
    },
    "8": {
      "User": 5,
      "n": 8,
      "EER": 0.13308248341456133,
      "AUC": 0.9392404457614583
    },
    "9": {
      "User": 5,
      "n": 9,
      "EER": 0.11971438134598011,
      "AUC": 0.941401772945341
    },
    "10": {
      "User": 5,
      "n": 10,
      "EER": 0.11874185743612228,
      "AUC": 0.9426546136555694
    }
  },
  "6": {
    "1": {
      "User": 6,
      "n": 1,
      "EER": 0.1764605688986428,
      "AUC": 0.9096566473568026
    },
    "2": {
      "User": 6,
      "n": 2,
      "EER": 0.15280898876403023,
      "AUC": 0.92894510637899
    },
    "3": {
      "User": 6,
      "n": 3,
      "EER": 0.14508037852012928,
      "AUC": 0.9369355740601154
    },
    "4": {
      "User": 6,
      "n": 4,
      "EER": 0.14027562752172673,
      "AUC": 0.9418849930073047
    },
    "5": {
      "User": 6,
      "n": 5,
      "EER": 0.1378071653368721,
      "AUC": 0.944522022926477
    },
    "6": {
      "User": 6,
      "n": 6,
      "EER": 0.1327112096996242,
      "AUC": 0.94710875555815
    },
    "7": {
      "User": 6,
      "n": 7,
      "EER": 0.13078149920255194,
      "AUC": 0.9491849475477062
    },
    "8": {
      "User": 6,
      "n": 8,
      "EER": 0.1284153005464481,
      "AUC": 0.9506914724148596
    },
    "9": {
      "User": 6,
      "n": 9,
      "EER": 0.12796697626441123,
      "AUC": 0.9514943065610779
    },
    "10": {
      "User": 6,
      "n": 10,
      "EER": 0.1308840413318028,
      "AUC": 0.9524481391372739
    }
  },
  "7": {
    "1": {
      "User": 7,
      "n": 1,
      "EER": 0.1711856141406341,
      "AUC": 0.9089049485244289
    },
    "2": {
      "User": 7,
      "n": 2,
      "EER": 0.13757557251954997,
      "AUC": 0.9356401104587836
    },
    "3": {
      "User": 7,
      "n": 3,
      "EER": 0.12277802262370116,
      "AUC": 0.9473259661725313
    },
    "4": {
      "User": 7,
      "n": 4,
      "EER": 0.11217183770883044,
      "AUC": 0.953977389183718
    },
    "5": {
      "User": 7,
      "n": 5,
      "EER": 0.10764646247444756,
      "AUC": 0.9584202847985066
    },
    "6": {
      "User": 7,
      "n": 6,
      "EER": 0.10233393177720951,
      "AUC": 0.9612973297113898
    },
    "7": {
      "User": 7,
      "n": 7,
      "EER": 0.10062893081761004,
      "AUC": 0.9636355382257176
    },
    "8": {
      "User": 7,
      "n": 8,
      "EER": 0.09175854056446142,
      "AUC": 0.9654072213392352
    },
    "9": {
      "User": 7,
      "n": 9,
      "EER": 0.08991825613079014,
      "AUC": 0.9660204097892323
    },
    "10": {
      "User": 7,
      "n": 10,
      "EER": 0.08786170147027805,
      "AUC": 0.9685401487748836
    }
  },
  "8": {
    "1": {
      "User": 8,
      "n": 1,
      "EER": 0.16482787429158094,
      "AUC": 0.9239114811535262
    },
    "2": {
      "User": 8,
      "n": 2,
      "EER": 0.12036238136324416,
      "AUC": 0.954780419321951
    },
    "3": {
      "User": 8,
      "n": 3,
      "EER": 0.09362808842652788,
      "AUC": 0.9693457411772486
    },
    "4": {
      "User": 8,
      "n": 4,
      "EER": 0.0838255282347091,
      "AUC": 0.9764411930250886
    },
    "5": {
      "User": 8,
      "n": 5,
      "EER": 0.07274701411509232,
      "AUC": 0.98093629267383
    },
    "6": {
      "User": 8,
      "n": 6,
      "EER": 0.06614771499990124,
      "AUC": 0.9832462799080407
    },
    "7": {
      "User": 8,
      "n": 7,
      "EER": 0.06447683271637822,
      "AUC": 0.9853795987298202
    },
    "8": {
      "User": 8,
      "n": 8,
      "EER": 0.05799648506151872,
      "AUC": 0.9868461183180539
    },
    "9": {
      "User": 8,
      "n": 9,
      "EER": 0.0540404040418672,
      "AUC": 0.9882109049771732
    },
    "10": {
      "User": 8,
      "n": 10,
      "EER": 0.0529801324505649,
      "AUC": 0.9897703064326324
    }
  },
  "9": {
    "1": {
      "User": 9,
      "n": 1,
      "EER": 0.16338549554077458,
      "AUC": 0.9135046757874916
    },
    "2": {
      "User": 9,
      "n": 2,
      "EER": 0.13575575950626417,
      "AUC": 0.9364562996742664
    },
    "3": {
      "User": 9,
      "n": 3,
      "EER": 0.12251082251076137,
      "AUC": 0.947292322337846
    },
    "4": {
      "User": 9,
      "n": 4,
      "EER": 0.11388310809273249,
      "AUC": 0.9539277386355088
    },
    "5": {
      "User": 9,
      "n": 5,
      "EER": 0.10720678285351445,
      "AUC": 0.9589055614766827
    },
    "6": {
      "User": 9,
      "n": 6,
      "EER": 0.10245183887916959,
      "AUC": 0.9623067123714404
    },
    "7": {
      "User": 9,
      "n": 7,
      "EER": 0.09814651368012776,
      "AUC": 0.964780707862486
    },
    "8": {
      "User": 9,
      "n": 8,
      "EER": 0.09342630488529537,
      "AUC": 0.9678528799254317
    },
    "9": {
      "User": 9,
      "n": 9,
      "EER": 0.0934210526315789,
      "AUC": 0.9687291340753661
    },
    "10": {
      "User": 9,
      "n": 10,
      "EER": 0.08651592881162319,
      "AUC": 0.9704319370321851
    }
  },
  "10": {
    "1": {
      "User": 10,
      "n": 1,
      "EER": 0.14032887572981942,
      "AUC": 0.9404266085975511
    },
    "2": {
      "User": 10,
      "n": 2,
      "EER": 0.09561806704668924,
      "AUC": 0.9641890552523629
    },
    "3": {
      "User": 10,
      "n": 3,
      "EER": 0.08003464543722016,
      "AUC": 0.9743830191672427
    },
    "4": {
      "User": 10,
      "n": 4,
      "EER": 0.07033864934155595,
      "AUC": 0.9800524927687257
    },
    "5": {
      "User": 10,
      "n": 5,
      "EER": 0.0625798212005109,
      "AUC": 0.9831861906764114
    },
    "6": {
      "User": 10,
      "n": 6,
      "EER": 0.05835435524649112,
      "AUC": 0.9861424416639099
    },
    "7": {
      "User": 10,
      "n": 7,
      "EER": 0.04856115107913992,
      "AUC": 0.9880361395459023
    },
    "8": {
      "User": 10,
      "n": 8,
      "EER": 0.047422680412372895,
      "AUC": 0.9891707576501392
    },
    "9": {
      "User": 10,
      "n": 9,
      "EER": 0.046003353828215056,
      "AUC": 0.990462031343809
    },
    "10": {
      "User": 10,
      "n": 10,
      "EER": 0.04599415749807989,
      "AUC": 0.9911180905173306
    }
  },
  "11": {
    "1": {
      "User": 11,
      "n": 1,
      "EER": 0.19643829385461825,
      "AUC": 0.8919762144904618
    },
    "2": {
      "User": 11,
      "n": 2,
      "EER": 0.16703038674015808,
      "AUC": 0.9194539751143671
    },
    "3": {
      "User": 11,
      "n": 3,
      "EER": 0.1497915826273988,
      "AUC": 0.9329137971540392
    },
    "4": {
      "User": 11,
      "n": 4,
      "EER": 0.14156099997353075,
      "AUC": 0.9408147546957919
    },
    "5": {
      "User": 11,
      "n": 5,
      "EER": 0.13147857303118687,
      "AUC": 0.9463500688424906
    },
    "6": {
      "User": 11,
      "n": 6,
      "EER": 0.1256537930469494,
      "AUC": 0.9507648446306123
    },
    "7": {
      "User": 11,
      "n": 7,
      "EER": 0.12252591894439663,
      "AUC": 0.9532593511596337
    },
    "8": {
      "User": 11,
      "n": 8,
      "EER": 0.12068965517238497,
      "AUC": 0.9560472927982134
    },
    "9": {
      "User": 11,
      "n": 9,
      "EER": 0.11488673139158327,
      "AUC": 0.9583432232805529
    },
    "10": {
      "User": 11,
      "n": 10,
      "EER": 0.11695906432750937,
      "AUC": 0.9592221827623489
    }
  },
  "12": {
    "1": {
      "User": 12,
      "n": 1,
      "EER": 0.23519194024628878,
      "AUC": 0.8570245058815664
    },
    "2": {
      "User": 12,
      "n": 2,
      "EER": 0.20086956521738128,
      "AUC": 0.888890275696449
    },
    "3": {
      "User": 12,
      "n": 3,
      "EER": 0.18552298506338383,
      "AUC": 0.9052406813697782
    },
    "4": {
      "User": 12,
      "n": 4,
      "EER": 0.1748948359971979,
      "AUC": 0.9155619421545567
    },
    "5": {
      "User": 12,
      "n": 5,
      "EER": 0.1601920558707437,
      "AUC": 0.923757555399679
    },
    "6": {
      "User": 12,
      "n": 6,
      "EER": 0.155578898225221,
      "AUC": 0.9297204366181591
    },
    "7": {
      "User": 12,
      "n": 7,
      "EER": 0.14701872386746273,
      "AUC": 0.9347864503690951
    },
    "8": {
      "User": 12,
      "n": 8,
      "EER": 0.13922996878301536,
      "AUC": 0.9384879420194607
    },
    "9": {
      "User": 12,
      "n": 9,
      "EER": 0.13601453948526931,
      "AUC": 0.9419841772100568
    },
    "10": {
      "User": 12,
      "n": 10,
      "EER": 0.13345039508340809,
      "AUC": 0.9450045478421196
    }
  },
  "13": {
    "1": {
      "User": 13,
      "n": 1,
      "EER": 0.28870683397283,
      "AUC": 0.7977972946324947
    },
    "2": {
      "User": 13,
      "n": 2,
      "EER": 0.25072068067815256,
      "AUC": 0.8357144294289525
    },
    "3": {
      "User": 13,
      "n": 3,
      "EER": 0.22995990070646083,
      "AUC": 0.8535070652028711
    },
    "4": {
      "User": 13,
      "n": 4,
      "EER": 0.22028262676641547,
      "AUC": 0.8651452534183542
    },
    "5": {
      "User": 13,
      "n": 5,
      "EER": 0.20644825793031657,
      "AUC": 0.8724263373090833
    },
    "6": {
      "User": 13,
      "n": 6,
      "EER": 0.19724700092271844,
      "AUC": 0.8793320244111963
    },
    "7": {
      "User": 13,
      "n": 7,
      "EER": 0.19110138584949737,
      "AUC": 0.8836706680995756
    },
    "8": {
      "User": 13,
      "n": 8,
      "EER": 0.186259384964023,
      "AUC": 0.8876462884279873
    },
    "9": {
      "User": 13,
      "n": 9,
      "EER": 0.1868227385987076,
      "AUC": 0.8904351802806563
    },
    "10": {
      "User": 13,
      "n": 10,
      "EER": 0.17536534446768878,
      "AUC": 0.893871510969585
    }
  },
  "14": {
    "1": {
      "User": 14,
      "n": 1,
      "EER": 0.23336211409420946,
      "AUC": 0.8491923909543229
    },
    "2": {
      "User": 14,
      "n": 2,
      "EER": 0.20262150341197102,
      "AUC": 0.8821643271362146
    },
    "3": {
      "User": 14,
      "n": 3,
      "EER": 0.18699153671106164,
      "AUC": 0.8964221530362857
    },
    "4": {
      "User": 14,
      "n": 4,
      "EER": 0.17922486720440695,
      "AUC": 0.9053613069605199
    },
    "5": {
      "User": 14,
      "n": 5,
      "EER": 0.1735313282355911,
      "AUC": 0.9116807019644937
    },
    "6": {
      "User": 14,
      "n": 6,
      "EER": 0.1665682220909627,
      "AUC": 0.9156252121370068
    },
    "7": {
      "User": 14,
      "n": 7,
      "EER": 0.16436940041351047,
      "AUC": 0.9199372601672978
    },
    "8": {
      "User": 14,
      "n": 8,
      "EER": 0.1607113271105307,
      "AUC": 0.9221973786592031
    },
    "9": {
      "User": 14,
      "n": 9,
      "EER": 0.15985060690840008,
      "AUC": 0.9245459814408704
    },
    "10": {
      "User": 14,
      "n": 10,
      "EER": 0.15555555555504502,
      "AUC": 0.9268192688993073
    }
  },
  "15": {
    "1": {
      "User": 15,
      "n": 1,
      "EER": 0.1889406219462252,
      "AUC": 0.8971216409832292
    },
    "2": {
      "User": 15,
      "n": 2,
      "EER": 0.16374875220687107,
      "AUC": 0.9218322136069391
    },
    "3": {
      "User": 15,
      "n": 3,
      "EER": 0.14582180409519582,
      "AUC": 0.932825635960009
    },
    "4": {
      "User": 15,
      "n": 4,
      "EER": 0.13779091244901265,
      "AUC": 0.9395278477587389
    },
    "5": {
      "User": 15,
      "n": 5,
      "EER": 0.13022761662352247,
      "AUC": 0.9442377657333347
    },
    "6": {
      "User": 15,
      "n": 6,
      "EER": 0.12444788841388799,
      "AUC": 0.9474846420422747
    },
    "7": {
      "User": 15,
      "n": 7,
      "EER": 0.12052500565697388,
      "AUC": 0.9501485312303267
    },
    "8": {
      "User": 15,
      "n": 8,
      "EER": 0.11410508860929579,
      "AUC": 0.952773858344753
    },
    "9": {
      "User": 15,
      "n": 9,
      "EER": 0.11204013377927977,
      "AUC": 0.9544724239426294
    },
    "10": {
      "User": 15,
      "n": 10,
      "EER": 0.11059479553880859,
      "AUC": 0.9561320725106252
    }
  },
  "16": {
    "1": {
      "User": 16,
      "n": 1,
      "EER": 0.19788076399907362,
      "AUC": 0.886907559975145
    },
    "2": {
      "User": 16,
      "n": 2,
      "EER": 0.18056811792529082,
      "AUC": 0.9060979294497274
    },
    "3": {
      "User": 16,
      "n": 3,
      "EER": 0.16820729578203036,
      "AUC": 0.9148366110895868
    },
    "4": {
      "User": 16,
      "n": 4,
      "EER": 0.1643678160915696,
      "AUC": 0.9205943916080049
    },
    "5": {
      "User": 16,
      "n": 5,
      "EER": 0.15873015873023774,
      "AUC": 0.924795560009209
    },
    "6": {
      "User": 16,
      "n": 6,
      "EER": 0.14850569610973147,
      "AUC": 0.9273105275041718
    },
    "7": {
      "User": 16,
      "n": 7,
      "EER": 0.14854180168473502,
      "AUC": 0.9301838361626142
    },
    "8": {
      "User": 16,
      "n": 8,
      "EER": 0.14849624060148708,
      "AUC": 0.9320423920493173
    },
    "9": {
      "User": 16,
      "n": 9,
      "EER": 0.14421897647516027,
      "AUC": 0.9331630128776899
    },
    "10": {
      "User": 16,
      "n": 10,
      "EER": 0.14246745195165783,
      "AUC": 0.9343551573494512
    }
  },
  "17": {
    "1": {
      "User": 17,
      "n": 1,
      "EER": 0.17695685869284392,
      "AUC": 0.8919447852171428
    },
    "2": {
      "User": 17,
      "n": 2,
      "EER": 0.16014945485721965,
      "AUC": 0.9064289443336588
    },
    "3": {
      "User": 17,
      "n": 3,
      "EER": 0.14735407341828113,
      "AUC": 0.9125710056721023
    },
    "4": {
      "User": 17,
      "n": 4,
      "EER": 0.14611398963730565,
      "AUC": 0.9168452732299953
    },
    "5": {
      "User": 17,
      "n": 5,
      "EER": 0.13972265023262756,
      "AUC": 0.9195027278507885
    },
    "6": {
      "User": 17,
      "n": 6,
      "EER": 0.1386292834890965,
      "AUC": 0.9219154454200248
    },
    "7": {
      "User": 17,
      "n": 7,
      "EER": 0.132596924410304,
      "AUC": 0.9237968888747378
    },
    "8": {
      "User": 17,
      "n": 8,
      "EER": 0.1343483435821709,
      "AUC": 0.9262826527258187
    },
    "9": {
      "User": 17,
      "n": 9,
      "EER": 0.13114754098386636,
      "AUC": 0.9268789510500035
    },
    "10": {
      "User": 17,
      "n": 10,
      "EER": 0.13220212567568462,
      "AUC": 0.9275611442600533
    }
  },
  "18": {
    "1": {
      "User": 18,
      "n": 1,
      "EER": 0.2453285111512851,
      "AUC": 0.8374071962190646
    },
    "2": {
      "User": 18,
      "n": 2,
      "EER": 0.20772946859941308,
      "AUC": 0.8654493744493865
    },
    "3": {
      "User": 18,
      "n": 3,
      "EER": 0.1872727272727357,
      "AUC": 0.8793475506303288
    },
    "4": {
      "User": 18,
      "n": 4,
      "EER": 0.1844679043798612,
      "AUC": 0.8864050172258995
    },
    "5": {
      "User": 18,
      "n": 5,
      "EER": 0.18098159509203893,
      "AUC": 0.8893407029301905
    },
    "6": {
      "User": 18,
      "n": 6,
      "EER": 0.17518248175181866,
      "AUC": 0.8939933624065162
    },
    "7": {
      "User": 18,
      "n": 7,
      "EER": 0.17625192274658358,
      "AUC": 0.8973871251009259
    },
    "8": {
      "User": 18,
      "n": 8,
      "EER": 0.18226600985218935,
      "AUC": 0.8979110909973333
    },
    "9": {
      "User": 18,
      "n": 9,
      "EER": 0.1833333333333335,
      "AUC": 0.8982820710689745
    },
    "10": {
      "User": 18,
      "n": 10,
      "EER": 0.16875000000001275,
      "AUC": 0.8994456108625022
    }
  },
  "19": {
    "1": {
      "User": 19,
      "n": 1,
      "EER": 0.248644713329604,
      "AUC": 0.8386691347664209
    },
    "2": {
      "User": 19,
      "n": 2,
      "EER": 0.21661237785017431,
      "AUC": 0.8757543396693193
    },
    "3": {
      "User": 19,
      "n": 3,
      "EER": 0.18918918918918912,
      "AUC": 0.8942033143258401
    },
    "4": {
      "User": 19,
      "n": 4,
      "EER": 0.1760797342193979,
      "AUC": 0.9098966171497405
    },
    "5": {
      "User": 19,
      "n": 5,
      "EER": 0.16536793911687345,
      "AUC": 0.918024677869878
    },
    "6": {
      "User": 19,
      "n": 6,
      "EER": 0.15015869541505192,
      "AUC": 0.9239864273393527
    },
    "7": {
      "User": 19,
      "n": 7,
      "EER": 0.1525546512120105,
      "AUC": 0.925416101119462
    },
    "8": {
      "User": 19,
      "n": 8,
      "EER": 0.12925170068031466,
      "AUC": 0.9383925294188316
    },
    "9": {
      "User": 19,
      "n": 9,
      "EER": 0.14952449013185456,
      "AUC": 0.9402107660822123
    },
    "10": {
      "User": 19,
      "n": 10,
      "EER": 0.12227928589016408,
      "AUC": 0.9431876851172523
    }
  },
  "20": {
    "1": {
      "User": 20,
      "n": 1,
      "EER": 0.026286356813575856,
      "AUC": 0.99705918268071
    },
    "2": {
      "User": 20,
      "n": 2,
      "EER": 0.009383201314220505,
      "AUC": 0.9991764054342697
    },
    "3": {
      "User": 20,
      "n": 3,
      "EER": 0.004324090590634494,
      "AUC": 0.9997434941876069
    },
    "4": {
      "User": 20,
      "n": 4,
      "EER": 0.00868623676718442,
      "AUC": 0.9997658290939089
    },
    "5": {
      "User": 20,
      "n": 5,
      "EER": 0.0028932220248248652,
      "AUC": 0.9998959530769904
    },
    "6": {
      "User": 20,
      "n": 6,
      "EER": 0.0010154493377245984,
      "AUC": 0.9999345196360501
    },
    "7": {
      "User": 20,
      "n": 7,
      "EER": 0.00042360316906742547,
      "AUC": 0.9999707859883757
    },
    "8": {
      "User": 20,
      "n": 8,
      "EER": 9.699321109674489e-05,
      "AUC": 0.9999961202715809
    },
    "9": {
      "User": 20,
      "n": 9,
      "EER": 0.00010928364679635088,
      "AUC": 0.9999947960168712
    },
    "10": {
      "User": 20,
      "n": 10,
      "EER": 0.00012155099169234497,
      "AUC": 0.99999360257944
    }
  },
  "21": {
    "1": {
      "User": 21,
      "n": 1,
      "EER": 0.1717557251912556,
      "AUC": 0.905980458163469
    },
    "2": {
      "User": 21,
      "n": 2,
      "EER": 0.1317014057200948,
      "AUC": 0.9364240040264243
    },
    "3": {
      "User": 21,
      "n": 3,
      "EER": 0.11277510566802408,
      "AUC": 0.9511242443762865
    },
    "4": {
      "User": 21,
      "n": 4,
      "EER": 0.10231660231660204,
      "AUC": 0.957415846218221
    },
    "5": {
      "User": 21,
      "n": 5,
      "EER": 0.09223300970874201,
      "AUC": 0.9626454305964759
    },
    "6": {
      "User": 21,
      "n": 6,
      "EER": 0.09411764705882358,
      "AUC": 0.9653982506093747
    },
    "7": {
      "User": 21,
      "n": 7,
      "EER": 0.09008738862298073,
      "AUC": 0.9676317489695514
    },
    "8": {
      "User": 21,
      "n": 8,
      "EER": 0.08356627924088691,
      "AUC": 0.9696133503394465
    },
    "9": {
      "User": 21,
      "n": 9,
      "EER": 0.0770760815517873,
      "AUC": 0.9712118970971069
    },
    "10": {
      "User": 21,
      "n": 10,
      "EER": 0.07424251736183597,
      "AUC": 0.972675677007809
    }
  },
  "22": {
    "1": {
      "User": 22,
      "n": 1,
      "EER": 0.16792323509252924,
      "AUC": 0.9130562178426692
    },
    "2": {
      "User": 22,
      "n": 2,
      "EER": 0.14102800407873892,
      "AUC": 0.9360469802989702
    },
    "3": {
      "User": 22,
      "n": 3,
      "EER": 0.126033057851242,
      "AUC": 0.9459083793899472
    },
    "4": {
      "User": 22,
      "n": 4,
      "EER": 0.11808118081180802,
      "AUC": 0.9526791709925883
    },
    "5": {
      "User": 22,
      "n": 5,
      "EER": 0.11061317838894498,
      "AUC": 0.9566918842468085
    },
    "6": {
      "User": 22,
      "n": 6,
      "EER": 0.10483451097091678,
      "AUC": 0.9600204020495021
    },
    "7": {
      "User": 22,
      "n": 7,
      "EER": 0.10227272727267628,
      "AUC": 0.9623946779762375
    },
    "8": {
      "User": 22,
      "n": 8,
      "EER": 0.0943405609697,
      "AUC": 0.964496421373003
    },
    "9": {
      "User": 22,
      "n": 9,
      "EER": 0.09250854485326024,
      "AUC": 0.9661402624058888
    },
    "10": {
      "User": 22,
      "n": 10,
      "EER": 0.08787784356457615,
      "AUC": 0.9675678509332688
    }
  },
  "23": {
    "1": {
      "User": 23,
      "n": 1,
      "EER": 0.1565637783562661,
      "AUC": 0.9167191917519604
    },
    "2": {
      "User": 23,
      "n": 2,
      "EER": 0.13124533929902563,
      "AUC": 0.9306806393986315
    },
    "3": {
      "User": 23,
      "n": 3,
      "EER": 0.12287662966991597,
      "AUC": 0.9373057273189913
    },
    "4": {
      "User": 23,
      "n": 4,
      "EER": 0.11606837606852999,
      "AUC": 0.9418500001833335
    },
    "5": {
      "User": 23,
      "n": 5,
      "EER": 0.11694707861759078,
      "AUC": 0.943661159439088
    },
    "6": {
      "User": 23,
      "n": 6,
      "EER": 0.11149556447305445,
      "AUC": 0.9465917312208469
    },
    "7": {
      "User": 23,
      "n": 7,
      "EER": 0.11248710010245509,
      "AUC": 0.949564232433509
    },
    "8": {
      "User": 23,
      "n": 8,
      "EER": 0.11145571801405692,
      "AUC": 0.951409537129466
    },
    "9": {
      "User": 23,
      "n": 9,
      "EER": 0.11379310344827576,
      "AUC": 0.9524347520117493
    },
    "10": {
      "User": 23,
      "n": 10,
      "EER": 0.11406844106462286,
      "AUC": 0.9530900279834773
    }
  },
  "24": {
    "1": {
      "User": 24,
      "n": 1,
      "EER": 0.1723815273175125,
      "AUC": 0.9089657436383203
    },
    "2": {
      "User": 24,
      "n": 2,
      "EER": 0.1471910112359548,
      "AUC": 0.9304465651334481
    },
    "3": {
      "User": 24,
      "n": 3,
      "EER": 0.1306878114442981,
      "AUC": 0.9402557106518421
    },
    "4": {
      "User": 24,
      "n": 4,
      "EER": 0.12446873102487647,
      "AUC": 0.9469605012618284
    },
    "5": {
      "User": 24,
      "n": 5,
      "EER": 0.1185579555824382,
      "AUC": 0.9510660073032143
    },
    "6": {
      "User": 24,
      "n": 6,
      "EER": 0.11388095761082996,
      "AUC": 0.9543390904887841
    },
    "7": {
      "User": 24,
      "n": 7,
      "EER": 0.10399999999999995,
      "AUC": 0.9576009578380227
    },
    "8": {
      "User": 24,
      "n": 8,
      "EER": 0.10550458715596328,
      "AUC": 0.9596614572456045
    },
    "9": {
      "User": 24,
      "n": 9,
      "EER": 0.10204081632653059,
      "AUC": 0.9615508898031241
    },
    "10": {
      "User": 24,
      "n": 10,
      "EER": 0.09714285714285673,
      "AUC": 0.9630690882316849
    }
  },
  "25": {
    "1": {
      "User": 25,
      "n": 1,
      "EER": 0.178776980597766,
      "AUC": 0.9050465850825704
    },
    "2": {
      "User": 25,
      "n": 2,
      "EER": 0.16136440966354607,
      "AUC": 0.9251717910404643
    },
    "3": {
      "User": 25,
      "n": 3,
      "EER": 0.14290934336931382,
      "AUC": 0.9341365869964322
    },
    "4": {
      "User": 25,
      "n": 4,
      "EER": 0.13285672457456765,
      "AUC": 0.9392997722791482
    },
    "5": {
      "User": 25,
      "n": 5,
      "EER": 0.1260391198051055,
      "AUC": 0.9443889535646756
    },
    "6": {
      "User": 25,
      "n": 6,
      "EER": 0.12713765584237058,
      "AUC": 0.9473758909943968
    },
    "7": {
      "User": 25,
      "n": 7,
      "EER": 0.12078651685390805,
      "AUC": 0.9509154552299317
    },
    "8": {
      "User": 25,
      "n": 8,
      "EER": 0.11202911379945289,
      "AUC": 0.9539375705461557
    },
    "9": {
      "User": 25,
      "n": 9,
      "EER": 0.10791366906474814,
      "AUC": 0.9559809035945706
    },
    "10": {
      "User": 25,
      "n": 10,
      "EER": 0.11089194353585272,
      "AUC": 0.9578479935893485
    }
  },
  "26": {
    "1": {
      "User": 26,
      "n": 1,
      "EER": 0.1882841328398112,
      "AUC": 0.8960885945793509
    },
    "2": {
      "User": 26,
      "n": 2,
      "EER": 0.16231469729149203,
      "AUC": 0.9182533394651013
    },
    "3": {
      "User": 26,
      "n": 3,
      "EER": 0.1523084333786379,
      "AUC": 0.9275545433145075
    },
    "4": {
      "User": 26,
      "n": 4,
      "EER": 0.14508746319562182,
      "AUC": 0.9334882143891797
    },
    "5": {
      "User": 26,
      "n": 5,
      "EER": 0.13949668381697225,
      "AUC": 0.9374233165391573
    },
    "6": {
      "User": 26,
      "n": 6,
      "EER": 0.13625177119783793,
      "AUC": 0.9404452647889892
    },
    "7": {
      "User": 26,
      "n": 7,
      "EER": 0.1389058280347094,
      "AUC": 0.942411318758045
    },
    "8": {
      "User": 26,
      "n": 8,
      "EER": 0.13444372413063194,
      "AUC": 0.9450521152729052
    },
    "9": {
      "User": 26,
      "n": 9,
      "EER": 0.1343635852764941,
      "AUC": 0.9458674136659713
    },
    "10": {
      "User": 26,
      "n": 10,
      "EER": 0.12924192238009502,
      "AUC": 0.9474462798405607
    }
  },
  "27": {
    "1": {
      "User": 27,
      "n": 1,
      "EER": 0.04106194690265976,
      "AUC": 0.9868700762468742
    },
    "2": {
      "User": 27,
      "n": 2,
      "EER": 0.02794683285563125,
      "AUC": 0.9897124673984968
    },
    "3": {
      "User": 27,
      "n": 3,
      "EER": 0.02397379353262538,
      "AUC": 0.9903959359516338
    },
    "4": {
      "User": 27,
      "n": 4,
      "EER": 0.023975950728109707,
      "AUC": 0.9908311453430722
    },
    "5": {
      "User": 27,
      "n": 5,
      "EER": 0.023082810347294917,
      "AUC": 0.9910485612882377
    },
    "6": {
      "User": 27,
      "n": 6,
      "EER": 0.022138726196217616,
      "AUC": 0.9910090340081888
    },
    "7": {
      "User": 27,
      "n": 7,
      "EER": 0.021256454389983505,
      "AUC": 0.991248869938629
    },
    "8": {
      "User": 27,
      "n": 8,
      "EER": 0.021082705285661283,
      "AUC": 0.9915133347767265
    },
    "9": {
      "User": 27,
      "n": 9,
      "EER": 0.02192495559646432,
      "AUC": 0.9916866742996785
    },
    "10": {
      "User": 27,
      "n": 10,
      "EER": 0.02173913043478252,
      "AUC": 0.9915870536053824
    }
  }
}